{
    "dataset": [
        {
            "label": "web services",
            "data": [
                {
                    "x": 201776,
                    "y": 74,
                    "r": 5
                },
                {
                    "x": 201407,
                    "y": 55,
                    "r": 5
                },
                {
                    "x": 201846,
                    "y": 37,
                    "r": 5
                },
                {
                    "x": 201576,
                    "y": 66,
                    "r": 5
                },
                {
                    "x": 201746,
                    "y": 50,
                    "r": 5
                },
                {
                    "x": 201769,
                    "y": 87,
                    "r": 5
                },
                {
                    "x": 201938,
                    "y": 63,
                    "r": 5
                },
                {
                    "x": 201346,
                    "y": 34,
                    "r": 5
                },
                {
                    "x": 201361,
                    "y": 77,
                    "r": 5
                },
                {
                    "x": 201692,
                    "y": 60,
                    "r": 5
                },
                {
                    "x": 201207,
                    "y": 77,
                    "r": 5
                },
                {
                    "x": 202107,
                    "y": 25,
                    "r": 5
                },
                {
                    "x": 202030,
                    "y": 26,
                    "r": 5
                },
                {
                    "x": 202069,
                    "y": 13,
                    "r": 5
                },
                {
                    "x": 201930,
                    "y": 81,
                    "r": 5
                }
            ],
            "backgroundColor": "#80008069",
            "hoverBackgroundColor": "#000000AA"
        },
        {
            "label": "AADHAR",
            "data": [
                {
                    "x": 201823,
                    "y": 64,
                    "r": 5
                }
            ],
            "backgroundColor": "#80008069",
            "hoverBackgroundColor": "#000000AA"
        },
        {
            "label": "social media",
            "data": [
                {
                    "x": 201930,
                    "y": 62,
                    "r": 5
                },
                {
                    "x": 201346,
                    "y": 76,
                    "r": 5
                },
                {
                    "x": 201838,
                    "y": 69,
                    "r": 5
                },
                {
                    "x": 201892,
                    "y": 71,
                    "r": 5
                },
                {
                    "x": 201892,
                    "y": 77,
                    "r": 5
                },
                {
                    "x": 201315,
                    "y": 73,
                    "r": 5
                }
            ],
            "backgroundColor": "#80008069",
            "hoverBackgroundColor": "#000000AA"
        },
        {
            "label": "e commerce",
            "data": [
                {
                    "x": 201376,
                    "y": 62,
                    "r": 5
                },
                {
                    "x": 201423,
                    "y": 66,
                    "r": 5
                },
                {
                    "x": 202107,
                    "y": 14,
                    "r": 5
                },
                {
                    "x": 201676,
                    "y": 82,
                    "r": 5
                },
                {
                    "x": 201907,
                    "y": 56,
                    "r": 5
                },
                {
                    "x": 201976,
                    "y": 87,
                    "r": 5
                },
                {
                    "x": 202084,
                    "y": 73,
                    "r": 5
                },
                {
                    "x": 202138,
                    "y": 46,
                    "r": 5
                }
            ],
            "backgroundColor": "#80008069",
            "hoverBackgroundColor": "#000000AA"
        },
        {
            "label": "health",
            "data": [
                {
                    "x": 201815,
                    "y": 95,
                    "r": 5
                },
                {
                    "x": 201846,
                    "y": 34,
                    "r": 5
                }
            ],
            "backgroundColor": "#80008069",
            "hoverBackgroundColor": "#000000AA"
        },
        {
            "label": "search engine",
            "data": [
                {
                    "x": 201423,
                    "y": 63,
                    "r": 5
                }
            ],
            "backgroundColor": "#80008069",
            "hoverBackgroundColor": "#000000AA"
        },
        {
            "label": "entertainment",
            "data": [
                {
                    "x": 201676,
                    "y": 36,
                    "r": 5
                },
                {
                    "x": 202030,
                    "y": 38,
                    "r": 5
                }
            ],
            "backgroundColor": "#80008069",
            "hoverBackgroundColor": "#000000AA"
        },
        {
            "label": "transport",
            "data": [
                {
                    "x": 201607,
                    "y": 44,
                    "r": 5
                }
            ],
            "backgroundColor": "#80008069",
            "hoverBackgroundColor": "#000000AA"
        },
        {
            "label": "education",
            "data": [
                {
                    "x": 202038,
                    "y": 86,
                    "r": 5
                }
            ],
            "backgroundColor": "#80008069",
            "hoverBackgroundColor": "#000000AA"
        },
        {
            "label": "airlines",
            "data": [
                {
                    "x": 202138,
                    "y": 59,
                    "r": 5
                }
            ],
            "backgroundColor": "#80008069",
            "hoverBackgroundColor": "#000000AA"
        },
        {
            "label": "NaN",
            "data": [
                {
                    "x": 201523,
                    "y": 38,
                    "r": 5
                },
                {
                    "x": 202023,
                    "y": 0,
                    "r": 5
                },
                {
                    "x": 201207,
                    "y": 94,
                    "r": 5
                },
                {
                    "x": 201630,
                    "y": 53,
                    "r": 5
                },
                {
                    "x": 201192,
                    "y": 6,
                    "r": 5
                },
                {
                    "x": 201815,
                    "y": 73,
                    "r": 5
                },
                {
                    "x": 201792,
                    "y": 18,
                    "r": 5
                },
                {
                    "x": 201853,
                    "y": 8,
                    "r": 5
                },
                {
                    "x": 201107,
                    "y": 61,
                    "r": 5
                },
                {
                    "x": 201853,
                    "y": 90,
                    "r": 5
                },
                {
                    "x": 201746,
                    "y": 67,
                    "r": 5
                },
                {
                    "x": 201584,
                    "y": 24,
                    "r": 5
                },
                {
                    "x": 201653,
                    "y": 27,
                    "r": 5
                },
                {
                    "x": 201484,
                    "y": 9,
                    "r": 5
                },
                {
                    "x": 201884,
                    "y": 61,
                    "r": 5
                },
                {
                    "x": 201376,
                    "y": 41,
                    "r": 8
                },
                {
                    "x": 201538,
                    "y": 76,
                    "r": 5
                },
                {
                    "x": 201676,
                    "y": 77,
                    "r": 9
                },
                {
                    "x": 201838,
                    "y": 87,
                    "r": 5
                },
                {
                    "x": 201830,
                    "y": 0,
                    "r": 5
                },
                {
                    "x": 201969,
                    "y": 68,
                    "r": 5
                },
                {
                    "x": 201338,
                    "y": 38,
                    "r": 5
                },
                {
                    "x": 201792,
                    "y": 8,
                    "r": 6
                },
                {
                    "x": 201669,
                    "y": 91,
                    "r": 5
                },
                {
                    "x": 201653,
                    "y": 33,
                    "r": 5
                },
                {
                    "x": 201584,
                    "y": 62,
                    "r": 5
                },
                {
                    "x": 201176,
                    "y": 56,
                    "r": 5
                },
                {
                    "x": 202076,
                    "y": 62,
                    "r": 5
                },
                {
                    "x": 202015,
                    "y": 61,
                    "r": 5
                },
                {
                    "x": 201607,
                    "y": 83,
                    "r": 5
                },
                {
                    "x": 201853,
                    "y": 53,
                    "r": 5
                },
                {
                    "x": 201692,
                    "y": 85,
                    "r": 10
                },
                {
                    "x": 201853,
                    "y": 45,
                    "r": 10
                },
                {
                    "x": 201723,
                    "y": 73,
                    "r": 5
                },
                {
                    "x": 202046,
                    "y": 18,
                    "r": 5
                },
                {
                    "x": 202030,
                    "y": 2,
                    "r": 5
                },
                {
                    "x": 201907,
                    "y": 60,
                    "r": 5
                },
                {
                    "x": 201638,
                    "y": 42,
                    "r": 5
                },
                {
                    "x": 201830,
                    "y": 19,
                    "r": 5
                },
                {
                    "x": 201946,
                    "y": 83,
                    "r": 5
                },
                {
                    "x": 201553,
                    "y": 76,
                    "r": 7
                },
                {
                    "x": 201392,
                    "y": 33,
                    "r": 5
                },
                {
                    "x": 201592,
                    "y": 88,
                    "r": 5
                },
                {
                    "x": 201861,
                    "y": 59,
                    "r": 5
                },
                {
                    "x": 201815,
                    "y": 43,
                    "r": 5
                },
                {
                    "x": 201438,
                    "y": 91,
                    "r": 5
                },
                {
                    "x": 201753,
                    "y": 97,
                    "r": 8
                },
                {
                    "x": 200876,
                    "y": 97,
                    "r": 5
                },
                {
                    "x": 201346,
                    "y": 24,
                    "r": 8
                },
                {
                    "x": 201892,
                    "y": 94,
                    "r": 5
                },
                {
                    "x": 201146,
                    "y": 75,
                    "r": 5
                },
                {
                    "x": 201584,
                    "y": 52,
                    "r": 5
                },
                {
                    "x": 201415,
                    "y": 55,
                    "r": 5
                },
                {
                    "x": 201738,
                    "y": 86,
                    "r": 5
                },
                {
                    "x": 201823,
                    "y": 90,
                    "r": 5
                },
                {
                    "x": 202076,
                    "y": 35,
                    "r": 6
                },
                {
                    "x": 201430,
                    "y": 45,
                    "r": 5
                },
                {
                    "x": 201469,
                    "y": 59,
                    "r": 5
                },
                {
                    "x": 201692,
                    "y": 72,
                    "r": 5
                },
                {
                    "x": 201407,
                    "y": 51,
                    "r": 5
                },
                {
                    "x": 201538,
                    "y": 31,
                    "r": 5
                },
                {
                    "x": 201438,
                    "y": 77,
                    "r": 5
                },
                {
                    "x": 201607,
                    "y": 25,
                    "r": 5
                },
                {
                    "x": 201446,
                    "y": 92,
                    "r": 5
                },
                {
                    "x": 201953,
                    "y": 34,
                    "r": 5
                },
                {
                    "x": 201892,
                    "y": 2,
                    "r": 5
                },
                {
                    "x": 201723,
                    "y": 63,
                    "r": 5
                },
                {
                    "x": 201892,
                    "y": 99,
                    "r": 5
                },
                {
                    "x": 202061,
                    "y": 13,
                    "r": 5
                },
                {
                    "x": 201853,
                    "y": 26,
                    "r": 5
                },
                {
                    "x": 201484,
                    "y": 77,
                    "r": 5
                },
                {
                    "x": 201423,
                    "y": 6,
                    "r": 5
                },
                {
                    "x": 201330,
                    "y": 10,
                    "r": 5
                },
                {
                    "x": 201476,
                    "y": 93,
                    "r": 5
                },
                {
                    "x": 201992,
                    "y": 55,
                    "r": 5
                },
                {
                    "x": 201776,
                    "y": 46,
                    "r": 5
                },
                {
                    "x": 201953,
                    "y": 16,
                    "r": 5
                },
                {
                    "x": 201430,
                    "y": 89,
                    "r": 5
                },
                {
                    "x": 201430,
                    "y": 3,
                    "r": 5
                },
                {
                    "x": 201915,
                    "y": 99,
                    "r": 5
                },
                {
                    "x": 201415,
                    "y": 43,
                    "r": 5
                },
                {
                    "x": 201938,
                    "y": 42,
                    "r": 9
                },
                {
                    "x": 202123,
                    "y": 23,
                    "r": 5
                },
                {
                    "x": 201684,
                    "y": 37,
                    "r": 5
                },
                {
                    "x": 202023,
                    "y": 23,
                    "r": 5
                },
                {
                    "x": 201623,
                    "y": 7,
                    "r": 5
                },
                {
                    "x": 202023,
                    "y": 30,
                    "r": 5
                },
                {
                    "x": 201553,
                    "y": 21,
                    "r": 5
                },
                {
                    "x": 201830,
                    "y": 30,
                    "r": 5
                },
                {
                    "x": 202076,
                    "y": 66,
                    "r": 5
                },
                {
                    "x": 202084,
                    "y": 4,
                    "r": 7
                },
                {
                    "x": 202115,
                    "y": 87,
                    "r": 5
                },
                {
                    "x": 201153,
                    "y": 4,
                    "r": 5
                },
                {
                    "x": 201653,
                    "y": 29,
                    "r": 5
                },
                {
                    "x": 201561,
                    "y": 81,
                    "r": 5
                },
                {
                    "x": 201669,
                    "y": 29,
                    "r": 5
                },
                {
                    "x": 201707,
                    "y": 39,
                    "r": 5
                },
                {
                    "x": 201807,
                    "y": 50,
                    "r": 5
                },
                {
                    "x": 201953,
                    "y": 33,
                    "r": 5
                },
                {
                    "x": 201715,
                    "y": 9,
                    "r": 5
                },
                {
                    "x": 201761,
                    "y": 49,
                    "r": 5
                },
                {
                    "x": 201907,
                    "y": 21,
                    "r": 14
                },
                {
                    "x": 201584,
                    "y": 83,
                    "r": 5
                },
                {
                    "x": 201623,
                    "y": 84,
                    "r": 5
                },
                {
                    "x": 201415,
                    "y": 81,
                    "r": 5
                },
                {
                    "x": 202015,
                    "y": 53,
                    "r": 5
                },
                {
                    "x": 201369,
                    "y": 63,
                    "r": 5
                },
                {
                    "x": 201953,
                    "y": 17,
                    "r": 5
                },
                {
                    "x": 201653,
                    "y": 50,
                    "r": 5
                },
                {
                    "x": 201838,
                    "y": 42,
                    "r": 5
                },
                {
                    "x": 201707,
                    "y": 85,
                    "r": 5
                },
                {
                    "x": 201661,
                    "y": 27,
                    "r": 5
                },
                {
                    "x": 201607,
                    "y": 35,
                    "r": 5
                },
                {
                    "x": 201738,
                    "y": 54,
                    "r": 5
                },
                {
                    "x": 202107,
                    "y": 2,
                    "r": 5
                },
                {
                    "x": 201676,
                    "y": 2,
                    "r": 6
                },
                {
                    "x": 201807,
                    "y": 25,
                    "r": 5
                },
                {
                    "x": 201146,
                    "y": 23,
                    "r": 5
                },
                {
                    "x": 201592,
                    "y": 83,
                    "r": 5
                },
                {
                    "x": 201884,
                    "y": 47,
                    "r": 6
                },
                {
                    "x": 201976,
                    "y": 33,
                    "r": 30
                },
                {
                    "x": 201692,
                    "y": 39,
                    "r": 5
                },
                {
                    "x": 201707,
                    "y": 99,
                    "r": 5
                },
                {
                    "x": 202046,
                    "y": 63,
                    "r": 5
                },
                {
                    "x": 201915,
                    "y": 5,
                    "r": 5
                },
                {
                    "x": 202123,
                    "y": 87,
                    "r": 5
                },
                {
                    "x": 201915,
                    "y": 4,
                    "r": 5
                },
                {
                    "x": 201461,
                    "y": 6,
                    "r": 5
                },
                {
                    "x": 201669,
                    "y": 60,
                    "r": 5
                },
                {
                    "x": 201253,
                    "y": 78,
                    "r": 5
                },
                {
                    "x": 201653,
                    "y": 52,
                    "r": 5
                },
                {
                    "x": 201192,
                    "y": 32,
                    "r": 5
                },
                {
                    "x": 201446,
                    "y": 30,
                    "r": 5
                },
                {
                    "x": 202123,
                    "y": 88,
                    "r": 5
                },
                {
                    "x": 202092,
                    "y": 23,
                    "r": 5
                },
                {
                    "x": 202053,
                    "y": 3,
                    "r": 5
                },
                {
                    "x": 201253,
                    "y": 96,
                    "r": 5
                },
                {
                    "x": 201892,
                    "y": 46,
                    "r": 11
                },
                {
                    "x": 201723,
                    "y": 76,
                    "r": 5
                },
                {
                    "x": 201330,
                    "y": 93,
                    "r": 5
                },
                {
                    "x": 202046,
                    "y": 16,
                    "r": 5
                },
                {
                    "x": 201107,
                    "y": 11,
                    "r": 5
                },
                {
                    "x": 201792,
                    "y": 34,
                    "r": 5
                },
                {
                    "x": 201938,
                    "y": 52,
                    "r": 5
                },
                {
                    "x": 201738,
                    "y": 56,
                    "r": 5
                },
                {
                    "x": 200907,
                    "y": 39,
                    "r": 5
                },
                {
                    "x": 201807,
                    "y": 50,
                    "r": 5
                },
                {
                    "x": 201876,
                    "y": 92,
                    "r": 5
                },
                {
                    "x": 202107,
                    "y": 84,
                    "r": 5
                },
                {
                    "x": 201830,
                    "y": 18,
                    "r": 5
                },
                {
                    "x": 201661,
                    "y": 14,
                    "r": 5
                },
                {
                    "x": 201969,
                    "y": 78,
                    "r": 5
                },
                {
                    "x": 201607,
                    "y": 88,
                    "r": 5
                },
                {
                    "x": 201546,
                    "y": 33,
                    "r": 5
                },
                {
                    "x": 201846,
                    "y": 49,
                    "r": 5
                },
                {
                    "x": 201669,
                    "y": 49,
                    "r": 5
                },
                {
                    "x": 201692,
                    "y": 88,
                    "r": 5
                },
                {
                    "x": 201961,
                    "y": 24,
                    "r": 5
                },
                {
                    "x": 201538,
                    "y": 70,
                    "r": 5
                },
                {
                    "x": 201923,
                    "y": 26,
                    "r": 5
                },
                {
                    "x": 201361,
                    "y": 72,
                    "r": 9
                },
                {
                    "x": 201646,
                    "y": 81,
                    "r": 5
                },
                {
                    "x": 201846,
                    "y": 34,
                    "r": 20
                },
                {
                    "x": 201569,
                    "y": 14,
                    "r": 5
                },
                {
                    "x": 202061,
                    "y": 17,
                    "r": 5
                },
                {
                    "x": 201676,
                    "y": 48,
                    "r": 11
                },
                {
                    "x": 201746,
                    "y": 7,
                    "r": 5
                },
                {
                    "x": 201815,
                    "y": 74,
                    "r": 5
                },
                {
                    "x": 201961,
                    "y": 55,
                    "r": 29
                },
                {
                    "x": 201646,
                    "y": 60,
                    "r": 5
                },
                {
                    "x": 201307,
                    "y": 66,
                    "r": 5
                },
                {
                    "x": 201723,
                    "y": 98,
                    "r": 5
                },
                {
                    "x": 201853,
                    "y": 52,
                    "r": 5
                },
                {
                    "x": 201692,
                    "y": 69,
                    "r": 5
                },
                {
                    "x": 202007,
                    "y": 0,
                    "r": 5
                },
                {
                    "x": 201569,
                    "y": 33,
                    "r": 5
                },
                {
                    "x": 201615,
                    "y": 21,
                    "r": 5
                },
                {
                    "x": 201953,
                    "y": 88,
                    "r": 5
                },
                {
                    "x": 201515,
                    "y": 75,
                    "r": 5
                },
                {
                    "x": 201123,
                    "y": 82,
                    "r": 7
                },
                {
                    "x": 201815,
                    "y": 8,
                    "r": 5
                },
                {
                    "x": 201630,
                    "y": 51,
                    "r": 5
                },
                {
                    "x": 201415,
                    "y": 56,
                    "r": 5
                },
                {
                    "x": 201646,
                    "y": 8,
                    "r": 5
                },
                {
                    "x": 200830,
                    "y": 8,
                    "r": 5
                },
                {
                    "x": 201707,
                    "y": 61,
                    "r": 5
                },
                {
                    "x": 201653,
                    "y": 98,
                    "r": 5
                },
                {
                    "x": 201438,
                    "y": 61,
                    "r": 5
                },
                {
                    "x": 201653,
                    "y": 19,
                    "r": 5
                },
                {
                    "x": 201830,
                    "y": 50,
                    "r": 5
                },
                {
                    "x": 201638,
                    "y": 68,
                    "r": 5
                },
                {
                    "x": 201538,
                    "y": 63,
                    "r": 5
                },
                {
                    "x": 202115,
                    "y": 49,
                    "r": 5
                },
                {
                    "x": 201576,
                    "y": 44,
                    "r": 5
                },
                {
                    "x": 201915,
                    "y": 11,
                    "r": 5
                },
                {
                    "x": 201523,
                    "y": 30,
                    "r": 5
                },
                {
                    "x": 201223,
                    "y": 38,
                    "r": 5
                },
                {
                    "x": 201946,
                    "y": 18,
                    "r": 5
                },
                {
                    "x": 201092,
                    "y": 95,
                    "r": 5
                },
                {
                    "x": 201738,
                    "y": 1,
                    "r": 5
                },
                {
                    "x": 201661,
                    "y": 38,
                    "r": 5
                },
                {
                    "x": 202076,
                    "y": 86,
                    "r": 5
                },
                {
                    "x": 201676,
                    "y": 26,
                    "r": 5
                },
                {
                    "x": 202023,
                    "y": 63,
                    "r": 5
                },
                {
                    "x": 201576,
                    "y": 12,
                    "r": 5
                },
                {
                    "x": 201876,
                    "y": 74,
                    "r": 5
                },
                {
                    "x": 200753,
                    "y": 94,
                    "r": 5
                },
                {
                    "x": 201653,
                    "y": 2,
                    "r": 5
                },
                {
                    "x": 201661,
                    "y": 35,
                    "r": 5
                },
                {
                    "x": 201630,
                    "y": 2,
                    "r": 5
                },
                {
                    "x": 201146,
                    "y": 40,
                    "r": 5
                },
                {
                    "x": 201553,
                    "y": 53,
                    "r": 5
                },
                {
                    "x": 201861,
                    "y": 97,
                    "r": 6
                },
                {
                    "x": 202046,
                    "y": 54,
                    "r": 5
                },
                {
                    "x": 201723,
                    "y": 96,
                    "r": 5
                },
                {
                    "x": 201553,
                    "y": 82,
                    "r": 5
                },
                {
                    "x": 201192,
                    "y": 33,
                    "r": 5
                },
                {
                    "x": 201307,
                    "y": 98,
                    "r": 5
                },
                {
                    "x": 201292,
                    "y": 36,
                    "r": 5
                },
                {
                    "x": 201407,
                    "y": 97,
                    "r": 5
                },
                {
                    "x": 201646,
                    "y": 71,
                    "r": 5
                },
                {
                    "x": 202015,
                    "y": 15,
                    "r": 5
                },
                {
                    "x": 201523,
                    "y": 75,
                    "r": 5
                },
                {
                    "x": 201976,
                    "y": 37,
                    "r": 5
                },
                {
                    "x": 201792,
                    "y": 66,
                    "r": 5
                },
                {
                    "x": 201838,
                    "y": 56,
                    "r": 7
                },
                {
                    "x": 202007,
                    "y": 73,
                    "r": 5
                },
                {
                    "x": 201861,
                    "y": 79,
                    "r": 5
                },
                {
                    "x": 201707,
                    "y": 9,
                    "r": 5
                },
                {
                    "x": 201923,
                    "y": 98,
                    "r": 5
                },
                {
                    "x": 201653,
                    "y": 30,
                    "r": 5
                },
                {
                    "x": 201892,
                    "y": 91,
                    "r": 5
                },
                {
                    "x": 201476,
                    "y": 93,
                    "r": 5
                },
                {
                    "x": 201369,
                    "y": 89,
                    "r": 6
                },
                {
                    "x": 201369,
                    "y": 62,
                    "r": 5
                },
                {
                    "x": 201976,
                    "y": 83,
                    "r": 5
                },
                {
                    "x": 201453,
                    "y": 51,
                    "r": 5
                },
                {
                    "x": 201923,
                    "y": 72,
                    "r": 5
                },
                {
                    "x": 201584,
                    "y": 68,
                    "r": 5
                },
                {
                    "x": 201553,
                    "y": 14,
                    "r": 5
                },
                {
                    "x": 201907,
                    "y": 73,
                    "r": 6
                },
                {
                    "x": 202023,
                    "y": 84,
                    "r": 5
                },
                {
                    "x": 201307,
                    "y": 74,
                    "r": 6
                },
                {
                    "x": 202061,
                    "y": 15,
                    "r": 5
                },
                {
                    "x": 201815,
                    "y": 88,
                    "r": 5
                },
                {
                    "x": 201223,
                    "y": 64,
                    "r": 5
                },
                {
                    "x": 201807,
                    "y": 3,
                    "r": 5
                },
                {
                    "x": 201669,
                    "y": 55,
                    "r": 5
                },
                {
                    "x": 201869,
                    "y": 95,
                    "r": 5
                },
                {
                    "x": 201415,
                    "y": 35,
                    "r": 5
                },
                {
                    "x": 201538,
                    "y": 99,
                    "r": 5
                },
                {
                    "x": 201969,
                    "y": 57,
                    "r": 5
                },
                {
                    "x": 201615,
                    "y": 70,
                    "r": 5
                },
                {
                    "x": 201630,
                    "y": 75,
                    "r": 5
                },
                {
                    "x": 201869,
                    "y": 7,
                    "r": 5
                },
                {
                    "x": 202046,
                    "y": 52,
                    "r": 5
                },
                {
                    "x": 201853,
                    "y": 6,
                    "r": 5
                },
                {
                    "x": 201223,
                    "y": 5,
                    "r": 5
                },
                {
                    "x": 202053,
                    "y": 56,
                    "r": 5
                },
                {
                    "x": 202023,
                    "y": 18,
                    "r": 7
                },
                {
                    "x": 201246,
                    "y": 22,
                    "r": 5
                },
                {
                    "x": 202046,
                    "y": 22,
                    "r": 5
                },
                {
                    "x": 201669,
                    "y": 68,
                    "r": 5
                },
                {
                    "x": 201915,
                    "y": 48,
                    "r": 5
                },
                {
                    "x": 201607,
                    "y": 5,
                    "r": 5
                },
                {
                    "x": 201846,
                    "y": 89,
                    "r": 5
                },
                {
                    "x": 202123,
                    "y": 29,
                    "r": 5
                },
                {
                    "x": 201238,
                    "y": 36,
                    "r": 6
                },
                {
                    "x": 201838,
                    "y": 93,
                    "r": 5
                },
                {
                    "x": 201615,
                    "y": 19,
                    "r": 5
                },
                {
                    "x": 201707,
                    "y": 71,
                    "r": 5
                },
                {
                    "x": 202046,
                    "y": 34,
                    "r": 5
                },
                {
                    "x": 201707,
                    "y": 69,
                    "r": 5
                },
                {
                    "x": 202061,
                    "y": 87,
                    "r": 5
                },
                {
                    "x": 201507,
                    "y": 55,
                    "r": 5
                },
                {
                    "x": 201261,
                    "y": 20,
                    "r": 5
                },
                {
                    "x": 201361,
                    "y": 54,
                    "r": 5
                },
                {
                    "x": 201361,
                    "y": 48,
                    "r": 5
                },
                {
                    "x": 201930,
                    "y": 86,
                    "r": 5
                },
                {
                    "x": 201792,
                    "y": 33,
                    "r": 5
                },
                {
                    "x": 201653,
                    "y": 68,
                    "r": 5
                },
                {
                    "x": 201576,
                    "y": 56,
                    "r": 5
                },
                {
                    "x": 201469,
                    "y": 53,
                    "r": 5
                },
                {
                    "x": 201584,
                    "y": 38,
                    "r": 5
                },
                {
                    "x": 201753,
                    "y": 83,
                    "r": 5
                },
                {
                    "x": 201484,
                    "y": 37,
                    "r": 5
                },
                {
                    "x": 201446,
                    "y": 73,
                    "r": 5
                },
                {
                    "x": 202123,
                    "y": 22,
                    "r": 5
                },
                {
                    "x": 201646,
                    "y": 26,
                    "r": 5
                },
                {
                    "x": 201892,
                    "y": 12,
                    "r": 5
                },
                {
                    "x": 202046,
                    "y": 63,
                    "r": 5
                },
                {
                    "x": 201723,
                    "y": 83,
                    "r": 5
                },
                {
                    "x": 201961,
                    "y": 97,
                    "r": 5
                },
                {
                    "x": 201615,
                    "y": 82,
                    "r": 9
                },
                {
                    "x": 202007,
                    "y": 24,
                    "r": 5
                },
                {
                    "x": 201676,
                    "y": 98,
                    "r": 5
                },
                {
                    "x": 201661,
                    "y": 70,
                    "r": 5
                },
                {
                    "x": 202007,
                    "y": 97,
                    "r": 5
                },
                {
                    "x": 201953,
                    "y": 17,
                    "r": 5
                },
                {
                    "x": 201923,
                    "y": 26,
                    "r": 5
                },
                {
                    "x": 201538,
                    "y": 74,
                    "r": 5
                },
                {
                    "x": 201607,
                    "y": 37,
                    "r": 5
                },
                {
                    "x": 201546,
                    "y": 7,
                    "r": 5
                },
                {
                    "x": 201938,
                    "y": 31,
                    "r": 5
                },
                {
                    "x": 202038,
                    "y": 48,
                    "r": 5
                },
                {
                    "x": 202007,
                    "y": 9,
                    "r": 5
                },
                {
                    "x": 201607,
                    "y": 66,
                    "r": 5
                },
                {
                    "x": 201676,
                    "y": 72,
                    "r": 7
                },
                {
                    "x": 200907,
                    "y": 33,
                    "r": 5
                },
                {
                    "x": 201769,
                    "y": 46,
                    "r": 5
                },
                {
                    "x": 201876,
                    "y": 47,
                    "r": 5
                },
                {
                    "x": 201846,
                    "y": 31,
                    "r": 5
                },
                {
                    "x": 201576,
                    "y": 61,
                    "r": 5
                },
                {
                    "x": 201692,
                    "y": 32,
                    "r": 5
                },
                {
                    "x": 201538,
                    "y": 57,
                    "r": 5
                },
                {
                    "x": 201415,
                    "y": 33,
                    "r": 5
                },
                {
                    "x": 201646,
                    "y": 0,
                    "r": 5
                },
                {
                    "x": 201515,
                    "y": 41,
                    "r": 5
                },
                {
                    "x": 201815,
                    "y": 1,
                    "r": 8
                },
                {
                    "x": 201776,
                    "y": 53,
                    "r": 6
                },
                {
                    "x": 201553,
                    "y": 70,
                    "r": 5
                },
                {
                    "x": 200853,
                    "y": 93,
                    "r": 11
                },
                {
                    "x": 201561,
                    "y": 37,
                    "r": 5
                },
                {
                    "x": 201576,
                    "y": 64,
                    "r": 5
                },
                {
                    "x": 201623,
                    "y": 59,
                    "r": 5
                },
                {
                    "x": 201669,
                    "y": 84,
                    "r": 5
                },
                {
                    "x": 201338,
                    "y": 26,
                    "r": 6
                },
                {
                    "x": 201576,
                    "y": 44,
                    "r": 7
                },
                {
                    "x": 201038,
                    "y": 10,
                    "r": 5
                },
                {
                    "x": 202092,
                    "y": 77,
                    "r": 5
                },
                {
                    "x": 201284,
                    "y": 45,
                    "r": 5
                },
                {
                    "x": 201669,
                    "y": 9,
                    "r": 6
                },
                {
                    "x": 201792,
                    "y": 72,
                    "r": 5
                },
                {
                    "x": 201430,
                    "y": 79,
                    "r": 5
                },
                {
                    "x": 201353,
                    "y": 53,
                    "r": 5
                },
                {
                    "x": 201592,
                    "y": 46,
                    "r": 5
                },
                {
                    "x": 202069,
                    "y": 91,
                    "r": 6
                },
                {
                    "x": 201615,
                    "y": 84,
                    "r": 5
                },
                {
                    "x": 201338,
                    "y": 42,
                    "r": 5
                },
                {
                    "x": 202038,
                    "y": 8,
                    "r": 5
                },
                {
                    "x": 201638,
                    "y": 72,
                    "r": 5
                },
                {
                    "x": 202115,
                    "y": 22,
                    "r": 5
                },
                {
                    "x": 201892,
                    "y": 72,
                    "r": 5
                },
                {
                    "x": 202030,
                    "y": 20,
                    "r": 5
                },
                {
                    "x": 201761,
                    "y": 62,
                    "r": 13
                },
                {
                    "x": 201607,
                    "y": 26,
                    "r": 5
                },
                {
                    "x": 201784,
                    "y": 48,
                    "r": 5
                },
                {
                    "x": 201938,
                    "y": 49,
                    "r": 5
                },
                {
                    "x": 201538,
                    "y": 97,
                    "r": 5
                },
                {
                    "x": 201361,
                    "y": 82,
                    "r": 5
                },
                {
                    "x": 202107,
                    "y": 41,
                    "r": 5
                },
                {
                    "x": 201076,
                    "y": 54,
                    "r": 5
                },
                {
                    "x": 202123,
                    "y": 78,
                    "r": 5
                },
                {
                    "x": 201576,
                    "y": 23,
                    "r": 5
                },
                {
                    "x": 201692,
                    "y": 9,
                    "r": 5
                },
                {
                    "x": 201907,
                    "y": 81,
                    "r": 5
                },
                {
                    "x": 201830,
                    "y": 57,
                    "r": 6
                },
                {
                    "x": 202092,
                    "y": 45,
                    "r": 5
                },
                {
                    "x": 201792,
                    "y": 45,
                    "r": 5
                },
                {
                    "x": 202130,
                    "y": 39,
                    "r": 5
                },
                {
                    "x": 201576,
                    "y": 24,
                    "r": 5
                },
                {
                    "x": 201392,
                    "y": 69,
                    "r": 5
                },
                {
                    "x": 202076,
                    "y": 22,
                    "r": 5
                },
                {
                    "x": 201792,
                    "y": 51,
                    "r": 6
                },
                {
                    "x": 201953,
                    "y": 42,
                    "r": 5
                },
                {
                    "x": 201553,
                    "y": 21,
                    "r": 5
                },
                {
                    "x": 201876,
                    "y": 56,
                    "r": 5
                },
                {
                    "x": 201553,
                    "y": 63,
                    "r": 5
                },
                {
                    "x": 201461,
                    "y": 4,
                    "r": 5
                },
                {
                    "x": 201676,
                    "y": 40,
                    "r": 5
                },
                {
                    "x": 201453,
                    "y": 8,
                    "r": 5
                },
                {
                    "x": 201838,
                    "y": 34,
                    "r": 6
                },
                {
                    "x": 201469,
                    "y": 58,
                    "r": 5
                },
                {
                    "x": 202046,
                    "y": 44,
                    "r": 5
                },
                {
                    "x": 201592,
                    "y": 86,
                    "r": 5
                },
                {
                    "x": 202046,
                    "y": 94,
                    "r": 5
                },
                {
                    "x": 201961,
                    "y": 43,
                    "r": 5
                },
                {
                    "x": 201807,
                    "y": 3,
                    "r": 5
                },
                {
                    "x": 201553,
                    "y": 57,
                    "r": 5
                },
                {
                    "x": 201569,
                    "y": 79,
                    "r": 5
                },
                {
                    "x": 201515,
                    "y": 78,
                    "r": 5
                },
                {
                    "x": 201553,
                    "y": 86,
                    "r": 5
                },
                {
                    "x": 201146,
                    "y": 72,
                    "r": 5
                },
                {
                    "x": 201423,
                    "y": 25,
                    "r": 5
                },
                {
                    "x": 201953,
                    "y": 22,
                    "r": 5
                },
                {
                    "x": 201592,
                    "y": 98,
                    "r": 5
                },
                {
                    "x": 201707,
                    "y": 70,
                    "r": 5
                },
                {
                    "x": 201584,
                    "y": 71,
                    "r": 5
                },
                {
                    "x": 201423,
                    "y": 63,
                    "r": 6
                },
                {
                    "x": 201684,
                    "y": 60,
                    "r": 5
                },
                {
                    "x": 201861,
                    "y": 9,
                    "r": 5
                },
                {
                    "x": 201669,
                    "y": 31,
                    "r": 5
                },
                {
                    "x": 201638,
                    "y": 37,
                    "r": 5
                },
                {
                    "x": 201738,
                    "y": 22,
                    "r": 5
                },
                {
                    "x": 201715,
                    "y": 2,
                    "r": 5
                },
                {
                    "x": 201407,
                    "y": 54,
                    "r": 5
                },
                {
                    "x": 201707,
                    "y": 66,
                    "r": 14
                },
                {
                    "x": 201892,
                    "y": 90,
                    "r": 5
                },
                {
                    "x": 201846,
                    "y": 19,
                    "r": 5
                },
                {
                    "x": 201638,
                    "y": 66,
                    "r": 5
                },
                {
                    "x": 201707,
                    "y": 76,
                    "r": 5
                },
                {
                    "x": 201869,
                    "y": 53,
                    "r": 5
                },
                {
                    "x": 201530,
                    "y": 76,
                    "r": 6
                },
                {
                    "x": 202046,
                    "y": 24,
                    "r": 5
                },
                {
                    "x": 201553,
                    "y": 60,
                    "r": 5
                },
                {
                    "x": 201707,
                    "y": 29,
                    "r": 5
                },
                {
                    "x": 201607,
                    "y": 58,
                    "r": 5
                },
                {
                    "x": 201853,
                    "y": 34,
                    "r": 5
                },
                {
                    "x": 201846,
                    "y": 16,
                    "r": 5
                },
                {
                    "x": 202069,
                    "y": 3,
                    "r": 5
                },
                {
                    "x": 201638,
                    "y": 41,
                    "r": 5
                },
                {
                    "x": 201615,
                    "y": 1,
                    "r": 5
                },
                {
                    "x": 202015,
                    "y": 60,
                    "r": 5
                },
                {
                    "x": 201769,
                    "y": 49,
                    "r": 5
                },
                {
                    "x": 201523,
                    "y": 76,
                    "r": 5
                },
                {
                    "x": 201407,
                    "y": 20,
                    "r": 5
                },
                {
                    "x": 201946,
                    "y": 43,
                    "r": 5
                },
                {
                    "x": 201884,
                    "y": 18,
                    "r": 5
                },
                {
                    "x": 201992,
                    "y": 34,
                    "r": 5
                },
                {
                    "x": 201146,
                    "y": 44,
                    "r": 5
                },
                {
                    "x": 201553,
                    "y": 6,
                    "r": 5
                },
                {
                    "x": 201576,
                    "y": 40,
                    "r": 6
                },
                {
                    "x": 201415,
                    "y": 11,
                    "r": 5
                },
                {
                    "x": 201861,
                    "y": 59,
                    "r": 5
                },
                {
                    "x": 201623,
                    "y": 17,
                    "r": 5
                },
                {
                    "x": 201515,
                    "y": 44,
                    "r": 5
                },
                {
                    "x": 201976,
                    "y": 17,
                    "r": 5
                },
                {
                    "x": 201723,
                    "y": 41,
                    "r": 5
                },
                {
                    "x": 201953,
                    "y": 26,
                    "r": 5
                },
                {
                    "x": 201561,
                    "y": 53,
                    "r": 5
                },
                {
                    "x": 202015,
                    "y": 24,
                    "r": 6
                },
                {
                    "x": 201192,
                    "y": 36,
                    "r": 5
                },
                {
                    "x": 201646,
                    "y": 50,
                    "r": 5
                },
                {
                    "x": 201853,
                    "y": 89,
                    "r": 5
                },
                {
                    "x": 201446,
                    "y": 70,
                    "r": 5
                },
                {
                    "x": 202115,
                    "y": 37,
                    "r": 5
                },
                {
                    "x": 201553,
                    "y": 49,
                    "r": 5
                },
                {
                    "x": 201530,
                    "y": 16,
                    "r": 5
                },
                {
                    "x": 202046,
                    "y": 71,
                    "r": 5
                },
                {
                    "x": 201984,
                    "y": 68,
                    "r": 5
                },
                {
                    "x": 202015,
                    "y": 66,
                    "r": 5
                },
                {
                    "x": 201207,
                    "y": 23,
                    "r": 5
                },
                {
                    "x": 201761,
                    "y": 77,
                    "r": 5
                },
                {
                    "x": 201492,
                    "y": 16,
                    "r": 5
                },
                {
                    "x": 201884,
                    "y": 84,
                    "r": 5
                },
                {
                    "x": 201530,
                    "y": 56,
                    "r": 5
                },
                {
                    "x": 201638,
                    "y": 55,
                    "r": 5
                },
                {
                    "x": 201415,
                    "y": 22,
                    "r": 5
                },
                {
                    "x": 201769,
                    "y": 3,
                    "r": 5
                },
                {
                    "x": 201569,
                    "y": 44,
                    "r": 5
                },
                {
                    "x": 201592,
                    "y": 17,
                    "r": 5
                },
                {
                    "x": 201792,
                    "y": 15,
                    "r": 5
                },
                {
                    "x": 201969,
                    "y": 60,
                    "r": 5
                },
                {
                    "x": 201784,
                    "y": 40,
                    "r": 5
                },
                {
                    "x": 201407,
                    "y": 40,
                    "r": 5
                },
                {
                    "x": 201192,
                    "y": 54,
                    "r": 5
                },
                {
                    "x": 202115,
                    "y": 8,
                    "r": 5
                },
                {
                    "x": 201838,
                    "y": 58,
                    "r": 5
                },
                {
                    "x": 202030,
                    "y": 18,
                    "r": 7
                },
                {
                    "x": 201961,
                    "y": 26,
                    "r": 5
                },
                {
                    "x": 201392,
                    "y": 44,
                    "r": 5
                },
                {
                    "x": 201469,
                    "y": 40,
                    "r": 5
                },
                {
                    "x": 202092,
                    "y": 94,
                    "r": 5
                },
                {
                    "x": 201846,
                    "y": 66,
                    "r": 5
                },
                {
                    "x": 201592,
                    "y": 15,
                    "r": 5
                },
                {
                    "x": 201615,
                    "y": 66,
                    "r": 5
                },
                {
                    "x": 202015,
                    "y": 50,
                    "r": 5
                },
                {
                    "x": 201315,
                    "y": 47,
                    "r": 5
                },
                {
                    "x": 201646,
                    "y": 83,
                    "r": 5
                },
                {
                    "x": 202007,
                    "y": 92,
                    "r": 5
                },
                {
                    "x": 201415,
                    "y": 72,
                    "r": 5
                },
                {
                    "x": 201730,
                    "y": 7,
                    "r": 5
                },
                {
                    "x": 202061,
                    "y": 39,
                    "r": 5
                },
                {
                    "x": 201984,
                    "y": 51,
                    "r": 5
                },
                {
                    "x": 201661,
                    "y": 40,
                    "r": 5
                },
                {
                    "x": 202107,
                    "y": 74,
                    "r": 5
                },
                {
                    "x": 202053,
                    "y": 46,
                    "r": 5
                },
                {
                    "x": 201607,
                    "y": 12,
                    "r": 5
                },
                {
                    "x": 201669,
                    "y": 96,
                    "r": 5
                },
                {
                    "x": 202046,
                    "y": 18,
                    "r": 5
                },
                {
                    "x": 201584,
                    "y": 37,
                    "r": 5
                },
                {
                    "x": 201953,
                    "y": 90,
                    "r": 5
                },
                {
                    "x": 201915,
                    "y": 38,
                    "r": 50
                },
                {
                    "x": 201407,
                    "y": 13,
                    "r": 5
                },
                {
                    "x": 202030,
                    "y": 66,
                    "r": 5
                },
                {
                    "x": 201707,
                    "y": 59,
                    "r": 5
                },
                {
                    "x": 201838,
                    "y": 94,
                    "r": 5
                },
                {
                    "x": 201207,
                    "y": 77,
                    "r": 7
                },
                {
                    "x": 201538,
                    "y": 16,
                    "r": 6
                },
                {
                    "x": 201384,
                    "y": 41,
                    "r": 5
                },
                {
                    "x": 201946,
                    "y": 21,
                    "r": 5
                },
                {
                    "x": 201584,
                    "y": 83,
                    "r": 5
                },
                {
                    "x": 201615,
                    "y": 59,
                    "r": 5
                },
                {
                    "x": 201892,
                    "y": 72,
                    "r": 5
                },
                {
                    "x": 201253,
                    "y": 6,
                    "r": 5
                },
                {
                    "x": 201484,
                    "y": 42,
                    "r": 5
                },
                {
                    "x": 201692,
                    "y": 55,
                    "r": 5
                },
                {
                    "x": 202046,
                    "y": 93,
                    "r": 22
                },
                {
                    "x": 201384,
                    "y": 16,
                    "r": 5
                },
                {
                    "x": 202107,
                    "y": 5,
                    "r": 5
                },
                {
                    "x": 202123,
                    "y": 95,
                    "r": 5
                },
                {
                    "x": 201646,
                    "y": 32,
                    "r": 5
                },
                {
                    "x": 201238,
                    "y": 60,
                    "r": 5
                },
                {
                    "x": 201946,
                    "y": 71,
                    "r": 5
                },
                {
                    "x": 201876,
                    "y": 79,
                    "r": 5
                },
                {
                    "x": 201569,
                    "y": 27,
                    "r": 5
                },
                {
                    "x": 201553,
                    "y": 45,
                    "r": 5
                },
                {
                    "x": 201369,
                    "y": 21,
                    "r": 5
                },
                {
                    "x": 201661,
                    "y": 82,
                    "r": 5
                },
                {
                    "x": 202007,
                    "y": 94,
                    "r": 5
                },
                {
                    "x": 202053,
                    "y": 41,
                    "r": 5
                },
                {
                    "x": 202076,
                    "y": 42,
                    "r": 5
                },
                {
                    "x": 201884,
                    "y": 67,
                    "r": 5
                },
                {
                    "x": 201407,
                    "y": 89,
                    "r": 5
                },
                {
                    "x": 201584,
                    "y": 85,
                    "r": 5
                },
                {
                    "x": 201569,
                    "y": 49,
                    "r": 5
                },
                {
                    "x": 201515,
                    "y": 35,
                    "r": 5
                },
                {
                    "x": 201684,
                    "y": 48,
                    "r": 5
                },
                {
                    "x": 201261,
                    "y": 68,
                    "r": 5
                },
                {
                    "x": 201953,
                    "y": 97,
                    "r": 5
                },
                {
                    "x": 201607,
                    "y": 30,
                    "r": 5
                },
                {
                    "x": 201384,
                    "y": 91,
                    "r": 5
                },
                {
                    "x": 201253,
                    "y": 70,
                    "r": 5
                },
                {
                    "x": 201346,
                    "y": 89,
                    "r": 5
                },
                {
                    "x": 201469,
                    "y": 71,
                    "r": 5
                },
                {
                    "x": 201369,
                    "y": 27,
                    "r": 5
                },
                {
                    "x": 201692,
                    "y": 95,
                    "r": 6
                },
                {
                    "x": 201915,
                    "y": 39,
                    "r": 5
                },
                {
                    "x": 201215,
                    "y": 1,
                    "r": 5
                },
                {
                    "x": 201876,
                    "y": 71,
                    "r": 7
                },
                {
                    "x": 201192,
                    "y": 80,
                    "r": 5
                },
                {
                    "x": 201738,
                    "y": 45,
                    "r": 5
                },
                {
                    "x": 201853,
                    "y": 12,
                    "r": 5
                },
                {
                    "x": 201107,
                    "y": 34,
                    "r": 5
                },
                {
                    "x": 202007,
                    "y": 70,
                    "r": 7
                },
                {
                    "x": 201969,
                    "y": 98,
                    "r": 5
                },
                {
                    "x": 201969,
                    "y": 26,
                    "r": 9
                },
                {
                    "x": 201661,
                    "y": 75,
                    "r": 5
                },
                {
                    "x": 201538,
                    "y": 53,
                    "r": 5
                },
                {
                    "x": 202023,
                    "y": 78,
                    "r": 5
                }
            ],
            "backgroundColor": "#80008069",
            "hoverBackgroundColor": "#000000AA"
        }
    ]
}